Metadata-Version: 2.1
Name: test-aws
Version: 0.0.7
Summary: tools for testing AWS cloud resources
Home-page: https://github.com/coalfire/test-aws
Author: Noah Birnel
Author-email: noah.birnel@coalfire.com
License: UNKNOWN
Platform: UNKNOWN
Classifier: Programming Language :: Python :: 3
Classifier: License :: OSI Approved :: MIT License
Classifier: Operating System :: OS Independent
Classifier: Development Status :: 3 - Alpha
Classifier: Environment :: Console
Classifier: Intended Audience :: System Administrators
Classifier: Intended Audience :: Information Technology
Classifier: Topic :: System :: Networking
Classifier: Topic :: Software Development :: Testing
Requires-Python: >=3.6
